LuizTools-0.1.data/scripts/main.py
gpython/__init__.py
gpython/gextension.py
gpython/hdirection.py
gpython/hmessage.py
gpython/hpacket.py
gpython/hparsers.py
gpython/htools.py
gpython/hunityparsers.py
gpython/hunitytools.py
LuizTools-0.1.dist-info/LICENSE.txt
LuizTools-0.1.dist-info/METADATA
LuizTools-0.1.dist-info/WHEEL
LuizTools-0.1.dist-info/top_level.txt
LuizTools-0.1.dist-info/RECORD
