Metadata-Version: 2.1
Name: LuizTools
Version: 0.1
Summary: LuizTools
Home-page: https://github.com/Luiz1n
Author: Luiz1n
Author-email: 
License: UNKNOWN
Platform: UNKNOWN
Classifier: Programming Language :: Python :: 3
Classifier: License :: OSI Approved :: MIT License
Classifier: Operating System :: OS Independent
